First_Task/__init__.py
First_Task/_modidx.py
First_Task/core.py
First_Task/my_module.py
First_Task/notebook_utils.py
First_Task-0.0.1.dist-info/LICENSE
First_Task-0.0.1.dist-info/METADATA
First_Task-0.0.1.dist-info/WHEEL
First_Task-0.0.1.dist-info/entry_points.txt
First_Task-0.0.1.dist-info/top_level.txt
First_Task-0.0.1.dist-info/RECORD
