Metadata-Version: 2.1
Name: First_Task
Version: 0.0.1
Summary: Working with nbdev and OpenVino.
Home-page: https://github.com/Romasha-Guin-Brysk/First_Task
Author: RomashaGuin
Author-email: romasha.guin@gmail.com
License: Apache Software License 2.0
Keywords: nbdev jupyter notebook python
Classifier: Development Status :: 4 - Beta
Classifier: Intended Audience :: Developers
Classifier: Natural Language :: English
Classifier: Programming Language :: Python :: 3.7
Classifier: Programming Language :: Python :: 3.8
Classifier: Programming Language :: Python :: 3.9
Classifier: Programming Language :: Python :: 3.10
Classifier: Programming Language :: Python :: 3.11
Classifier: Programming Language :: Python :: 3.12
Classifier: License :: OSI Approved :: Apache Software License
Requires-Python: >=3.7
License-File: LICENSE
Requires-Dist: openvino
Requires-Dist: ipywidgets (==8.1.5)
Requires-Dist: opencv-python (==4.9.0.80)
Requires-Dist: numpy (==1.26.4)
Requires-Dist: pillow (==10.4.0)
Requires-Dist: requests (==2.31.0)
Requires-Dist: ultralytics (==8.3.61)
Requires-Dist: nncf (==2.14.1)
Provides-Extra: dev
